rllib/__init__.py
rllib/_base.py
rllib/frame_buffer.py
rllib/qlearning.py
rllib/replay_buffer.py
rllib/trainer.py
rllib/utils.py
pytorch_rllib-0.1.2.dist-info/LICENSE
pytorch_rllib-0.1.2.dist-info/METADATA
pytorch_rllib-0.1.2.dist-info/WHEEL
pytorch_rllib-0.1.2.dist-info/top_level.txt
pytorch_rllib-0.1.2.dist-info/RECORD
