Metadata-Version: 2.1
Name: pytorch-rllib
Version: 0.1.2
Summary: Reinforcement Learning Library.
Home-page: https://github.com/dayyass/rllib
Author: Dani El-Ayyass
Author-email: dayyass@yandex.ru
License: UNKNOWN
Platform: UNKNOWN
Requires-Dist: gym (==0.25.1)
Requires-Dist: gym[accept-rom-license,atari] (==0.25.1)
Requires-Dist: numpy (==1.21.6)
Requires-Dist: Pillow (==9.2.0)
Requires-Dist: torch (==1.12.1)
Requires-Dist: tqdm (==4.64.0)
